LICENSE
README.md
setup.cfg
setup.py
superloops/__init__.py
superloops/superloops.py
superloops.egg-info/PKG-INFO
superloops.egg-info/SOURCES.txt
superloops.egg-info/dependency_links.txt
superloops.egg-info/top_level.txt
test/test_superloops.py