Metadata-Version: 2.1
Name: superloops
Version: 0.1.2
Summary: SuperLoops package simplifies and augments usage of Python threads. It provides support for thread maintenance, events, failure handling, health status propagation, and graceful termination.
Home-page: https://github.com/Voyz/superloops
Author: Voy Zan
Author-email: voy1982@yahoo.co.uk
License: Apache-2.0
Keywords: thread,threads,python threads,threading,multithreading,asynchronous,concurrency,thread management
Classifier: Development Status :: 4 - Beta
Classifier: Intended Audience :: Developers
Classifier: Topic :: Software Development :: Libraries :: Python Modules
Classifier: Programming Language :: Python :: 3.6
License-File: LICENSE
